README.md
setup.cfg
setup.py
argmaxtools/__init__.py
argmaxtools/_positional_encoding.py
argmaxtools/_sdpa.py
argmaxtools/_version.py
argmaxtools/nn.py
argmaxtools/tensor_typing.py
argmaxtools/test_utils.py
argmaxtools/utils.py
argmaxtools.egg-info/PKG-INFO
argmaxtools.egg-info/SOURCES.txt
argmaxtools.egg-info/dependency_links.txt
argmaxtools.egg-info/requires.txt
argmaxtools.egg-info/top_level.txt
argmaxtools/compress/__init__.py
argmaxtools/compress/palettize.py
argmaxtools/compress/sparse_outlier.py
argmaxtools/compress/utils.py
argmaxtools/coreml/__init__.py
argmaxtools/coreml/coreml_load.py
argmaxtools/coreml/coreml_metadata.py
argmaxtools/coreml/coreml_model.py
argmaxtools/finetune/__init__.py
argmaxtools/finetune/enc_dec_qlora_finetuner.py
argmaxtools/finetune/finetuner.py
argmaxtools/finetune/lora.py
tests/test_attention.py