Metadata-Version: 2.4
Name: argmaxtools
Version: 0.1.23
Summary: Argmax Model Optimization Toolkit
Home-page: https://github.com/argmaxinc/argmaxtools
Author: Argmax, Inc.
Classifier: Development Status :: 4 - Beta
Classifier: Intended Audience :: Developers
Classifier: Operating System :: MacOS :: MacOS X
Classifier: Programming Language :: Python :: 3
Classifier: Programming Language :: Python :: 3.9
Classifier: Programming Language :: Python :: 3.10
Classifier: Programming Language :: Python :: 3.11
Classifier: Programming Language :: Python :: 3.12
Classifier: Topic :: Scientific/Engineering
Classifier: Topic :: Software Development
Requires-Dist: beartype
Requires-Dist: coremltools>=8.1
Requires-Dist: jaxtyping
Requires-Dist: scikit-learn
Requires-Dist: torch
Requires-Dist: wandb
Requires-Dist: tabulate
Requires-Dist: huggingface-hub
Dynamic: author
Dynamic: classifier
Dynamic: description
Dynamic: description-content-type
Dynamic: home-page
Dynamic: requires-dist
Dynamic: summary
